setup.cfg
setup.py
pyctu/__init__.py
pyctu/ui.py
pyctu/window.py
pyctu.egg-info/PKG-INFO
pyctu.egg-info/SOURCES.txt
pyctu.egg-info/dependency_links.txt
pyctu.egg-info/entry_points.txt
pyctu.egg-info/not-zip-safe
pyctu.egg-info/requires.txt
pyctu.egg-info/top_level.txt
pyctu/commands/__init__.py
pyctu/commands/api.py
pyctu/commands/api_packet.py
pyctu/commands/at.py
pyctu/commands/command_base.py
pyctu/commands/definitions.py
pyctu/commands/firmware.py
pyctu/commands/xmodem.py
pyctu/dialogs/__init__.py
pyctu/dialogs/bits.py
pyctu/dialogs/confirm.py
pyctu/dialogs/firmware_update.py
pyctu/dialogs/help.py
pyctu/dialogs/multiline.py
pyctu/dialogs/page_select.py
pyctu/dialogs/prompt.py
pyctu/dialogs/reset.py
pyctu/dialogs/select.py