Metadata-Version: 1.0
Name: pyctu
Version: 0.1dev
Summary: A curses interface to configure xbees
Home-page: UNKNOWN
Author: Craig Swank
Author-email: craigswank@gmail.com
License: MIT
Keywords: xbee x-ctu
Platform: UNKNOWN
